{
    "deckId":  "gandalf_the_white",
    "nation":  "Gandalf",
    "alignment":  0,
    "handSize":  5,
    "cards":  [
                  {
                      "cardId":  614,
                      "name":  "Gondorian Archers",
                      "type":  "Army",
                      "spriteName":  "GondorianArchers",
                      "tags":  [

                               ],
                      "troopType":  1,
                      "race":  0,
                      "specialAbilities":  [
                                               0
                                           ],
                      "commanderSkillRequired":  1,
                      "agentSkillRequired":  0,
                      "emissarySkillRequired":  0,
                      "mageSkillRequired":  0,
                      "difficulty":  0,
                      "leatherRequired":  0,
                      "mountsRequired":  0,
                      "timberRequired":  0,
                      "ironRequired":  1,
                      "steelRequired":  0,
                      "mithrilRequired":  0,
                      "goldRequired":  4,
                      "jokerRequired":  0,
                      "quote":  ""
                  },
                  {
                      "cardId":  615,
                      "name":  "Gondorian Infantry",
                      "type":  "Army",
                      "spriteName":  "GondorianInfrantry",
                      "tags":  [

                               ],
                      "troopType":  3,
                      "race":  0,
                      "specialAbilities":  [

                                           ],
                      "commanderSkillRequired":  1,
                      "agentSkillRequired":  0,
                      "emissarySkillRequired":  0,
                      "mageSkillRequired":  0,
                      "difficulty":  0,
                      "leatherRequired":  0,
                      "mountsRequired":  0,
                      "timberRequired":  0,
                      "ironRequired":  2,
                      "steelRequired":  0,
                      "mithrilRequired":  0,
                      "goldRequired":  3,
                      "jokerRequired":  0,
                      "quote":  ""
                  },
                  {
                      "cardId":  631,
                      "name":  "Knights Of Dol Amroth",
                      "type":  "Army",
                      "spriteName":  "KnightsOfDolAmroth",
                      "tags":  [

                               ],
                      "troopType":  5,
                      "race":  0,
                      "specialAbilities":  [
                                               11
                                           ],
                      "commanderSkillRequired":  1,
                      "agentSkillRequired":  0,
                      "emissarySkillRequired":  0,
                      "mageSkillRequired":  0,
                      "difficulty":  0,
                      "leatherRequired":  0,
                      "mountsRequired":  1,
                      "timberRequired":  0,
                      "ironRequired":  1,
                      "steelRequired":  1,
                      "mithrilRequired":  0,
                      "goldRequired":  6,
                      "jokerRequired":  0,
                      "quote":  ""
                  },
                  {
                      "cardId":  638,
                      "name":  "Meduseld Guards",
                      "type":  "Army",
                      "spriteName":  "MeduseldGuards",
                      "tags":  [

                               ],
                      "troopType":  0,
                      "race":  0,
                      "specialAbilities":  [
                                               8
                                           ],
                      "commanderSkillRequired":  1,
                      "agentSkillRequired":  0,
                      "emissarySkillRequired":  0,
                      "mageSkillRequired":  0,
                      "difficulty":  0,
                      "leatherRequired":  0,
                      "mountsRequired":  0,
                      "timberRequired":  0,
                      "ironRequired":  1,
                      "steelRequired":  0,
                      "mithrilRequired":  0,
                      "goldRequired":  3,
                      "jokerRequired":  0,
                      "quote":  ""
                  },
                  {
                      "cardId":  655,
                      "name":  "Pelargir Fleet",
                      "type":  "Army",
                      "spriteName":  "PelargirFleet",
                      "tags":  [

                               ],
                      "troopType":  7,
                      "race":  0,
                      "specialAbilities":  [

                                           ],
                      "commanderSkillRequired":  1,
                      "agentSkillRequired":  0,
                      "emissarySkillRequired":  0,
                      "mageSkillRequired":  0,
                      "difficulty":  0,
                      "leatherRequired":  0,
                      "mountsRequired":  0,
                      "timberRequired":  1,
                      "ironRequired":  1,
                      "steelRequired":  1,
                      "mithrilRequired":  0,
                      "goldRequired":  4,
                      "jokerRequired":  0,
                      "quote":  ""
                  },
                  {
                      "cardId":  658,
                      "name":  "Rangers Of Ithilien",
                      "type":  "Army",
                      "spriteName":  "RangersOfIthilien",
                      "tags":  [

                               ],
                      "troopType":  1,
                      "race":  0,
                      "specialAbilities":  [
                                               5
                                           ],
                      "commanderSkillRequired":  1,
                      "agentSkillRequired":  0,
                      "emissarySkillRequired":  0,
                      "mageSkillRequired":  0,
                      "difficulty":  0,
                      "leatherRequired":  0,
                      "mountsRequired":  0,
                      "timberRequired":  0,
                      "ironRequired":  1,
                      "steelRequired":  0,
                      "mithrilRequired":  0,
                      "goldRequired":  4,
                      "jokerRequired":  0,
                      "quote":  ""
                  },
                  {
                      "cardId":  662,
                      "name":  "Riders Of Rohan",
                      "type":  "Army",
                      "spriteName":  "RidersOfRohan",
                      "tags":  [

                               ],
                      "troopType":  4,
                      "race":  0,
                      "specialAbilities":  [
                                               11
                                           ],
                      "commanderSkillRequired":  1,
                      "agentSkillRequired":  0,
                      "emissarySkillRequired":  0,
                      "mageSkillRequired":  0,
                      "difficulty":  0,
                      "leatherRequired":  0,
                      "mountsRequired":  1,
                      "timberRequired":  0,
                      "ironRequired":  1,
                      "steelRequired":  0,
                      "mithrilRequired":  0,
                      "goldRequired":  4,
                      "jokerRequired":  0,
                      "quote":  ""
                  },
                  {
                      "cardId":  673,
                      "name":  "Swan Fleet",
                      "type":  "Army",
                      "spriteName":  "SwanFleet",
                      "tags":  [

                               ],
                      "troopType":  7,
                      "race":  0,
                      "specialAbilities":  [

                                           ],
                      "commanderSkillRequired":  1,
                      "agentSkillRequired":  0,
                      "emissarySkillRequired":  0,
                      "mageSkillRequired":  0,
                      "difficulty":  0,
                      "leatherRequired":  0,
                      "mountsRequired":  0,
                      "timberRequired":  1,
                      "ironRequired":  1,
                      "steelRequired":  1,
                      "mithrilRequired":  0,
                      "goldRequired":  4,
                      "jokerRequired":  0,
                      "quote":  ""
                  },
                  {
                      "cardId":  679,
                      "name":  "Tower Guards",
                      "type":  "Army",
                      "spriteName":  "TowerGuards",
                      "tags":  [

                               ],
                      "troopType":  3,
                      "race":  0,
                      "specialAbilities":  [
                                               7
                                           ],
                      "commanderSkillRequired":  1,
                      "agentSkillRequired":  0,
                      "emissarySkillRequired":  0,
                      "mageSkillRequired":  0,
                      "difficulty":  0,
                      "leatherRequired":  0,
                      "mountsRequired":  0,
                      "timberRequired":  0,
                      "ironRequired":  2,
                      "steelRequired":  0,
                      "mithrilRequired":  0,
                      "goldRequired":  3,
                      "jokerRequired":  0,
                      "quote":  ""
                  },
                  {
                      "cardId":  692,
                      "name":  "White Tower Wardens",
                      "type":  "Army",
                      "spriteName":  "WhiteTowerWardens",
                      "tags":  [

                               ],
                      "troopType":  3,
                      "race":  0,
                      "specialAbilities":  [
                                               7
                                           ],
                      "commanderSkillRequired":  1,
                      "agentSkillRequired":  0,
                      "emissarySkillRequired":  0,
                      "mageSkillRequired":  0,
                      "difficulty":  0,
                      "leatherRequired":  0,
                      "mountsRequired":  0,
                      "timberRequired":  0,
                      "ironRequired":  2,
                      "steelRequired":  0,
                      "mithrilRequired":  0,
                      "goldRequired":  3,
                      "jokerRequired":  0,
                      "quote":  ""
                  },
                  {
                      "cardId":  680,
                      "name":  "Trebuchets",
                      "type":  "Army",
                      "spriteName":  "Trebuchets",
                      "tags":  [

                               ],
                      "troopType":  6,
                      "race":  21,
                      "specialAbilities":  [

                                           ],
                      "commanderSkillRequired":  1,
                      "agentSkillRequired":  0,
                      "emissarySkillRequired":  0,
                      "mageSkillRequired":  0,
                      "difficulty":  0,
                      "leatherRequired":  0,
                      "mountsRequired":  0,
                      "timberRequired":  1,
                      "ironRequired":  1,
                      "steelRequired":  0,
                      "mithrilRequired":  0,
                      "goldRequired":  4,
                      "jokerRequired":  0,
                      "quote":  ""
                  },
                  {
                      "cardId":  700,
                      "name":  "Woses",
                      "type":  "Army",
                      "spriteName":  "Woses",
                      "tags":  [

                               ],
                      "troopType":  2,
                      "race":  15,
                      "specialAbilities":  [

                                           ],
                      "commanderSkillRequired":  1,
                      "agentSkillRequired":  0,
                      "emissarySkillRequired":  0,
                      "mageSkillRequired":  0,
                      "difficulty":  0,
                      "leatherRequired":  1,
                      "mountsRequired":  0,
                      "timberRequired":  0,
                      "ironRequired":  0,
                      "steelRequired":  0,
                      "mithrilRequired":  0,
                      "goldRequired":  2,
                      "jokerRequired":  0,
                      "quote":  ""
                  },
                  {
                      "cardId":  28,
                      "name":  "Minas Tirith",
                      "type":  "PC",
                      "action":  "PCAction",
                      "tags":  [
                                   "NorthernGondor"
                               ],
                      "region":  "NorthernGondor",
                      "spriteName":  "MinasTirith",
                      "goldGranted":  0,
                      "leatherGranted":  0,
                      "timberGranted":  0,
                      "mountsGranted":  0,
                      "ironGranted":  2,
                      "steelGranted":  0,
                      "mithrilGranted":  0,
                      "deckId":  "GandalfTheWhite",
                      "quote":  "Minas Tirith rises white against the long shadow of the East, steadfast as a horn-call at dawn."
                  },
                  {
                      "cardId":  29,
                      "name":  "Henneth Annun",
                      "type":  "PC",
                      "action":  "PCAction",
                      "tags":  [
                                   "Ithilien"
                               ],
                      "region":  "Ithilien",
                      "spriteName":  "HennethAnnun",
                      "goldGranted":  0,
                      "leatherGranted":  0,
                      "timberGranted":  0,
                      "mountsGranted":  2,
                      "ironGranted":  0,
                      "steelGranted":  0,
                      "mithrilGranted":  0,
                      "deckId":  "GandalfTheWhite",
                      "mountsRequired":  1,
                      "ironRequired":  1,
                      "quote":  "Henneth Annun hides the stream in shadow, as though the land itself guarded the hidden door."
                  },
                  {
                      "cardId":  127,
                      "name":  "Ithilien",
                      "type":  "Land",
                      "action":  "MaterialRetrieval",
                      "tags":  [

                               ],
                      "goldGranted":  2,
                      "leatherGranted":  2,
                      "timberGranted":  0,
                      "mountsGranted":  1,
                      "ironGranted":  0,
                      "steelGranted":  0,
                      "mithrilGranted":  0,
                      "deckId":  "GandalfTheWhite"
                  },
                  {
                      "cardId":  131,
                      "name":  "NorthernGondor",
                      "type":  "Land",
                      "action":  "MaterialRetrieval",
                      "tags":  [

                               ],
                      "goldGranted":  2,
                      "leatherGranted":  0,
                      "timberGranted":  0,
                      "mountsGranted":  1,
                      "ironGranted":  2,
                      "steelGranted":  0,
                      "mithrilGranted":  0,
                      "deckId":  "GandalfTheWhite"
                  },
                  {
                      "cardId":  136,
                      "name":  "SouthernGondor",
                      "type":  "Land",
                      "action":  "MaterialRetrieval",
                      "tags":  [

                               ],
                      "goldGranted":  3,
                      "leatherGranted":  0,
                      "timberGranted":  0,
                      "mountsGranted":  1,
                      "ironGranted":  1,
                      "steelGranted":  0,
                      "mithrilGranted":  0,
                      "deckId":  "GandalfTheWhite"
                  },
                  {
                      "cardId":  310,
                      "name":  "CairAndros",
                      "type":  "PC",
                      "action":  "PCAction",
                      "spriteName":  "CairAndros",
                      "tags":  [
                                   "Nindalf"
                               ],
                      "region":  "Nindalf",
                      "goldGranted":  2,
                      "leatherGranted":  0,
                      "timberGranted":  0,
                      "mountsGranted":  0,
                      "ironGranted":  0,
                      "steelGranted":  0,
                      "mithrilGranted":  0,
                      "deckId":  "GandalfTheWhite",
                      "quote":  "CairAndros holds the river like a spear-point, watching north and south with hard patience."
                  },
                  {
                      "cardId":  327,
                      "name":  "DolAmroth",
                      "type":  "PC",
                      "action":  "PCAction",
                      "spriteName":  "DolAmroth",
                      "tags":  [
                                   "SouthernGondor"
                               ],
                      "region":  "SouthernGondor",
                      "goldGranted":  2,
                      "leatherGranted":  0,
                      "timberGranted":  0,
                      "mountsGranted":  1,
                      "ironGranted":  0,
                      "steelGranted":  0,
                      "mithrilGranted":  0,
                      "deckId":  "GandalfTheWhite",
                      "quote":  "DolAmroth shines like a white helm set upon the sea, bright against the long road of dusk."
                  },
                  {
                      "cardId":  333,
                      "name":  "Erech",
                      "type":  "PC",
                      "action":  "PCAction",
                      "spriteName":  "Erech",
                      "tags":  [
                                   "SouthernGondor"
                               ],
                      "region":  "SouthernGondor",
                      "goldGranted":  0,
                      "leatherGranted":  0,
                      "timberGranted":  1,
                      "mountsGranted":  0,
                      "ironGranted":  1,
                      "steelGranted":  0,
                      "mithrilGranted":  0,
                      "deckId":  "GandalfTheWhite",
                      "quote":  "Erech remembers the oath-stones, and even the wind there speaks with old restraint."
                  },
                  {
                      "cardId":  352,
                      "name":  "Imdorad",
                      "type":  "PC",
                      "action":  "PCAction",
                      "spriteName":  "Imdorad",
                      "tags":  [
                                   "NorthernGondor"
                               ],
                      "region":  "NorthernGondor",
                      "goldGranted":  0,
                      "leatherGranted":  1,
                      "timberGranted":  0,
                      "mountsGranted":  0,
                      "ironGranted":  1,
                      "steelGranted":  0,
                      "mithrilGranted":  0,
                      "deckId":  "GandalfTheWhite",
                      "quote":  "Imdorad feels like a hall built for men who kept faith when the world forgot them."
                  },
                  {
                      "cardId":  361,
                      "name":  "Linhir",
                      "type":  "PC",
                      "action":  "PCAction",
                      "spriteName":  "Linhir",
                      "tags":  [
                                   "SouthernGondor"
                               ],
                      "region":  "SouthernGondor",
                      "goldGranted":  0,
                      "leatherGranted":  0,
                      "timberGranted":  1,
                      "mountsGranted":  0,
                      "ironGranted":  1,
                      "steelGranted":  0,
                      "mithrilGranted":  0,
                      "deckId":  "GandalfTheWhite",
                      "quote":  "Linhir keeps its harbor face to the tides, with Gondor’s old courage under the salt air."
                  },
                  {
                      "cardId":  366,
                      "name":  "MinasArthor",
                      "type":  "PC",
                      "action":  "PCAction",
                      "spriteName":  "MinasArthor",
                      "tags":  [
                                   "SouthernGondor"
                               ],
                      "region":  "SouthernGondor",
                      "goldGranted":  0,
                      "leatherGranted":  0,
                      "timberGranted":  0,
                      "mountsGranted":  0,
                      "ironGranted":  2,
                      "steelGranted":  1,
                      "mithrilGranted":  0,
                      "deckId":  "GandalfTheWhite",
                      "quote":  "MinasArthor stands in stern splendor, and its towers hold the wind like a vow."
                  },
                  {
                      "cardId":  367,
                      "name":  "Morthondost",
                      "type":  "PC",
                      "action":  "PCAction",
                      "spriteName":  "Morthondost",
                      "tags":  [
                                   "SouthernGondor"
                               ],
                      "region":  "SouthernGondor",
                      "goldGranted":  0,
                      "leatherGranted":  0,
                      "timberGranted":  0,
                      "mountsGranted":  0,
                      "ironGranted":  2,
                      "steelGranted":  1,
                      "mithrilGranted":  0,
                      "deckId":  "GandalfTheWhite",
                      "quote":  "Morthondost stands as if carved from the will of the men who would not yield the river-road."
                  },
                  {
                      "cardId":  377,
                      "name":  "Osgiliath",
                      "type":  "PC",
                      "action":  "PCAction",
                      "spriteName":  "Osgiliath",
                      "tags":  [
                                   "Ithilien"
                               ],
                      "region":  "Ithilien",
                      "goldGranted":  2,
                      "leatherGranted":  0,
                      "timberGranted":  0,
                      "mountsGranted":  0,
                      "ironGranted":  1,
                      "steelGranted":  0,
                      "mithrilGranted":  0,
                      "deckId":  "GandalfTheWhite",
                      "quote":  "Osgiliath bears its wounds openly, yet the river still remembers the city that once was."
                  },
                  {
                      "cardId":  380,
                      "name":  "Pelargir",
                      "type":  "PC",
                      "action":  "PCAction",
                      "spriteName":  "Pelargir",
                      "tags":  [
                                   "SouthernGondor"
                               ],
                      "region":  "SouthernGondor",
                      "goldGranted":  0,
                      "leatherGranted":  0,
                      "timberGranted":  1,
                      "mountsGranted":  0,
                      "ironGranted":  1,
                      "steelGranted":  0,
                      "mithrilGranted":  0,
                      "deckId":  "GandalfTheWhite",
                      "quote":  "Pelargir wears the scars of trade and war alike, yet the tide still brings and carries its memory."
                  },
                  {
                      "cardId":  849,
                      "name":  "Nindalf",
                      "type":  "Land",
                      "action":  "MaterialRetrieval",
                      "spriteName":  "Nindalf",
                      "tags":  [

                               ],
                      "goldGranted":  0,
                      "leatherGranted":  3,
                      "timberGranted":  1,
                      "mountsGranted":  0,
                      "ironGranted":  0,
                      "steelGranted":  1,
                      "mithrilGranted":  0,
                      "deckId":  "GandalfTheWhite"
                  }
              ]
}